gmtu/__init__.py
gmtu/cli.py
gmtu/gmtu.py
gmtu-0.1.3.dist-info/METADATA
gmtu-0.1.3.dist-info/WHEEL
gmtu-0.1.3.dist-info/entry_points.txt
gmtu-0.1.3.dist-info/top_level.txt
gmtu-0.1.3.dist-info/RECORD
