Metadata-Version: 2.4
Name: gmtu
Version: 0.1.3
Summary: Send push notification to your phone, with the GMTU app
Author-email: Xuan Tang <txstc55@gmail.com>
License: MIT
Requires-Python: >=3.7
